[
    {
        "id": "pbc_3554030554",
        "listRule": null,
        "viewRule": null,
        "createRule": null,
        "updateRule": null,
        "deleteRule": null,
        "name": "invitations",
        "type": "base",
        "fields": [
            {
                "autogeneratePattern": "[a-z0-9]{15}",
                "hidden": false,
                "id": "text3208210256",
                "max": 15,
                "min": 15,
                "name": "id",
                "pattern": "^[a-z0-9]+$",
                "presentable": true,
                "primaryKey": true,
                "required": true,
                "system": true,
                "type": "text"
            },
            {
                "autogeneratePattern": "",
                "hidden": false,
                "id": "text1111111111",
                "max": 15,
                "min": 15,
                "name": "appointment",
                "pattern": "^[a-z0-9]+$",
                "presentable": false,
                "primaryKey": false,
                "required": true,
                "system": false,
                "type": "text"
            },
            {
                "autogeneratePattern": "",
                "hidden": false,
                "id": "text2222222222",
                "max": 15,
                "min": 15,
                "name": "guest",
                "pattern": "^[a-z0-9]+$",
                "presentable": false,
                "primaryKey": false,
                "required": true,
                "system": false,
                "type": "text"
            },
            {
                "autogeneratePattern": "",
                "hidden": false,
                "id": "text3333333333",
                "max": 30,
                "min": 0,
                "name": "status",
                "pattern": "",
                "presentable": false,
                "primaryKey": false,
                "required": true,
                "system": false,
                "type": "text"
            },
            {
                "hidden": false,
                "id": "date4444444444",
                "max": "",
                "min": "",
                "name": "respondedAt",
                "presentable": false,
                "required": false,
                "system": false,
                "type": "date"
            },
            {
                "hidden": false,
                "id": "autodate5555555555",
                "name": "created",
                "onCreate": true,
                "onUpdate": false,
                "presentable": false,
                "system": false,
                "type": "autodate"
            },
            {
                "hidden": false,
                "id": "autodate6666666666",
                "name": "updated",
                "onCreate": true,
                "onUpdate": true,
                "presentable": false,
                "system": false,
                "type": "autodate"
            }
        ],
        "indexes": [
            "CREATE INDEX idx_appointment ON invitations (appointment)",
            "CREATE INDEX idx_guest ON invitations (guest)",
            "CREATE INDEX idx_status ON invitations (status)"
        ],
        "system": false
    }
]

